logtweet/__init__.py
logtweet/conf.py
logtweet-0.1.4.dist-info/LICENSE
logtweet-0.1.4.dist-info/METADATA
logtweet-0.1.4.dist-info/WHEEL
logtweet-0.1.4.dist-info/entry_points.txt
logtweet-0.1.4.dist-info/top_level.txt
logtweet-0.1.4.dist-info/RECORD
