Metadata-Version: 2.1
Name: logtweet
Version: 0.1.4
Summary: Create a tweet based on a #100DaysOfCode log message
Home-page: https://github.com/tbrlpld/100daysofweb-with-python-course/tree/master/work/078-twitter-bot
Author: Tibor Leupold
Author-email: tibor@lpld.io
License: UNKNOWN
Platform: UNKNOWN
Requires-Python: >=3.6
Requires-Dist: bs4
Requires-Dist: requests
Requires-Dist: tweepy
Provides-Extra: develop
Requires-Dist: wheel ; extra == 'develop'
Requires-Dist: twine ; extra == 'develop'
